ripflow/__init__.py
ripflow/analyzers/__init__.py
ripflow/analyzers/base.py
ripflow/connectors/__init__.py
ripflow/connectors/sink/__init__.py
ripflow/connectors/sink/base.py
ripflow/connectors/sink/zmq_sink_connector.py
ripflow/connectors/source/__init__.py
ripflow/connectors/source/base.py
ripflow/connectors/source/pydoocs_source_connector.py
ripflow/core/__init__.py
ripflow/core/processes.py
ripflow/core/ripflow.py
ripflow/core/supervisor.py
ripflow/core/utils.py
ripflow/serializers/__init__.py
ripflow/serializers/avro_serializer.py
ripflow/serializers/base.py
ripflow/serializers/json_serializer.py
ripflow-0.3.0.dist-info/METADATA
ripflow-0.3.0.dist-info/WHEEL
ripflow-0.3.0.dist-info/LICENSE
ripflow-0.3.0.dist-info/RECORD
