Metadata-Version: 2.1
Name: ripflow
Version: 0.3.0
Summary: Python package to insert analysis pipelines into data streams
Home-page: https://github.com/soerenjalas/ripflow
Author: Soeren Jalas
Author-email: soeren.jalas@desy.de
Requires-Python: >=3.9,<4.0
Classifier: Programming Language :: Python :: 3
Classifier: Programming Language :: Python :: 3.9
Classifier: Programming Language :: Python :: 3.10
Classifier: Programming Language :: Python :: 3.11
Requires-Dist: avro (>=1.11.1,<2.0.0)
Requires-Dist: numpy (>=1.24.2,<2.0.0)
Requires-Dist: pyzmq (>=25.0.0,<26.0.0)
Project-URL: Repository, https://github.com/soerenjalas/ripflow
